chatbot_ner/LICENSE.txt
chatbot_ner/README.md
chatbot_ner/__init__.py
chatbot_ner/datastore_exceptions.py
chatbot_ner/datastore_setup.py
chatbot_ner/manage.py
chatbot_ner/ner_constants.py
chatbot_ner/nltk_setup.py
chatbot_ner/requirements.txt
chatbot_ner/run_postman_tests.sh
chatbot_ner/setup.py
chatbot_ner/chatbot_ner/__init__.py
chatbot_ner/chatbot_ner/config.py
chatbot_ner/chatbot_ner/settings.py
chatbot_ner/chatbot_ner/urls.py
chatbot_ner/chatbot_ner/wsgi.py
chatbot_ner/data/__init__.py
chatbot_ner/data/entity_data/__init__.py
chatbot_ner/data/entity_data/airport_code.csv
chatbot_ner/data/entity_data/brand.csv
chatbot_ner/data/entity_data/budget.csv
chatbot_ner/data/entity_data/city.csv
chatbot_ner/data/entity_data/clothes.csv
chatbot_ner/data/entity_data/cuisine.csv
chatbot_ner/data/entity_data/day_list.csv
chatbot_ner/data/entity_data/dish.csv
chatbot_ner/data/entity_data/footwear.csv
chatbot_ner/data/entity_data/locality.csv
chatbot_ner/data/entity_data/month_list.csv
chatbot_ner/data/entity_data/movie.csv
chatbot_ner/data/entity_data/restaurant.csv
chatbot_ner/data/entity_data/shopping_size.csv
chatbot_ner/data/models/__init__.py
chatbot_ner/data/models/crf/__init__.py
chatbot_ner/data/models/crf/city/__init__.py
chatbot_ner/data/models/crf/city/model_13062017.crf
chatbot_ner/data/models/crf/date/__init__.py
chatbot_ner/data/models/crf/date/model_date.crf
chatbot_ner/datastore/__init__.py
chatbot_ner/datastore/constants.py
chatbot_ner/datastore/datastore.py
chatbot_ner/datastore/exceptions.py
chatbot_ner/datastore/utils.py
chatbot_ner/datastore/commands/__init__.py
chatbot_ner/datastore/commands/create_datastore.py
chatbot_ner/datastore/commands/delete_datastore.py
chatbot_ner/datastore/commands/delete_entity_data_datastore.py
chatbot_ner/datastore/commands/populate_datastore.py
chatbot_ner/datastore/commands/repopulate_datastore.py
chatbot_ner/datastore/elastic_search/__init__.py
chatbot_ner-0.0.7.dist-info/DESCRIPTION.rst
chatbot_ner-0.0.7.dist-info/METADATA
chatbot_ner-0.0.7.dist-info/RECORD
chatbot_ner-0.0.7.dist-info/WHEEL
chatbot_ner-0.0.7.dist-info/metadata.json
chatbot_ner-0.0.7.dist-info/top_level.txt
